ranjg/__init__.py
ranjg/__main__.py
ranjg/_arg_parser.py
ranjg/_context.py
ranjg/_gen.py
ranjg/_number_range.py
ranjg/factories.py
ranjg/options.py
ranjg/error/__init__.py
ranjg/error/_generate_error.py
ranjg/error/_invalid_schema_error.py
ranjg/error/_options_file_io_error.py
ranjg/error/_schema_confrict_error.py
ranjg/error/_schema_file_io_error.py
ranjg/schemas/__init__.py
ranjg/schemas/_io.py
ranjg/schemas/_validate.py
ranjg/schemas/normalize.py
ranjg/util/__init__.py
ranjg/util/listutil.py
ranjg/util/numutil.py
ranjg-0.5.1.0.dist-info/METADATA
ranjg-0.5.1.0.dist-info/WHEEL
ranjg-0.5.1.0.dist-info/top_level.txt
ranjg-0.5.1.0.dist-info/RECORD
