Metadata-Version: 2.4
Name: ranjg
Version: 0.5.1.0
Summary: Generate json text randomly
Author: k-izumi
Author-email: k.izumi.ysk@gmail.com
Maintainer: k-izumi
Maintainer-email: k.izumi.ysk@gmail.com
License: MIT
Project-URL: Bug Tracker, https://github.com/unaguna/random-json-generator/issues
Project-URL: Documentation, https://unaguna.github.io/random-json-generator/
Project-URL: Source Code, https://github.com/unaguna/random-json-generator
Classifier: Development Status :: 2 - Pre-Alpha
Classifier: Programming Language :: Python :: 3.6
Classifier: License :: OSI Approved :: MIT License
Classifier: Topic :: Utilities
Requires-Dist: jsonschema
Requires-Dist: rstr
Dynamic: author
Dynamic: author-email
Dynamic: classifier
Dynamic: description
Dynamic: description-content-type
Dynamic: license
Dynamic: maintainer
Dynamic: maintainer-email
Dynamic: project-url
Dynamic: requires-dist
Dynamic: summary
